README.txt
eyam.py
setup.py
eyam.egg-info/PKG-INFO
eyam.egg-info/SOURCES.txt
eyam.egg-info/dependency_links.txt
eyam.egg-info/top_level.txt