Metadata-Version: 1.0
Name: eyam
Version: 0.1
Summary: A Python Mocking Isolation Library for Testing
Home-page: http://github.com/akaihola/eyam/
Author: Antti Kaihola
Author-email: akaihol+python@ambitone.com
License: UNKNOWN
Keywords: testing,test,mock,mocking,unittest,patching,stubs,fakes,doubles
Platform: UNKNOWN
Classifier: Development Status :: 4 - Beta
Classifier: Environment :: Console
Classifier: Intended Audience :: Developers
Classifier: License :: OSI Approved :: BSD License
Classifier: Programming Language :: Python
Classifier: Programming Language :: Python :: 2
Classifier: Programming Language :: Python :: 2.6
Classifier: Operating System :: OS Independent
Classifier: Topic :: Software Development :: Libraries
Classifier: Topic :: Software Development :: Libraries :: Python Modules
Classifier: Topic :: Software Development :: Testing
